{
  "todo_list": [
    {
      "course_nm": "대학생활과 진로설계",
      "due_date": "20250616140000",
      "info": "20250616140000",
      "item_title_temp": "자신의 포트폴리오 작성하기",
      "type": "과제"
    },
    {
      "course_nm": "물리학 1",
      "due_date": "20250614235900",
      "info": "20250614235900",
      "item_title_temp": "07장 회전운동과 중력  ",
      "type": "과제"
    },
    {
      "course_nm": "물리학 1",
      "due_date": "20250615235900",
      "info": "20250615235900",
      "item_title_temp": "8장 회전평형과 회전 동역학",
      "type": "과제"
    },
    {
      "course_nm": "물리학 1",
      "due_date": "20250615235900",
      "info": "20250615235900",
      "item_title_temp": "9장 고체와 유체",
      "type": "과제"
    },
    {
      "course_nm": "물리학 1",
      "due_date": "20250615235900",
      "info": "20250615235900",
      "item_title_temp": "10장 열물리학",
      "type": "과제"
    },
    {
      "course_nm": "물리학 1",
      "due_date": "20250615235900",
      "info": "20250615235900",
      "item_title_temp": "11장 열과정에서의 에너지",
      "type": "과제"
    },
    {
      "course_nm": "물리학 1",
      "due_date": "20250615235900",
      "info": "20250615235900",
      "item_title_temp": "12장 열역학법칙",
      "type": "과제"
    },
    {
      "course_nm": "물리학 1",
      "due_date": "20250615235900",
      "info": "20250615235900",
      "item_title_temp": "13장 진동과 파동",
      "type": "과제"
    },
    {
      "course_nm": "컴퓨터과학적사고",
      "due_date": "20250608235900",
      "info": "20250531235900",
      "item_title_temp": "[필독] SW중심사업단 모두들 위한 SW 지식플러스(명사초청강연) 일정2 & 보고서",
      "type": "과제"
    }
  ],
  "user_no": "bd7d272fc91e0e04ebb2e80040e6aa46f4b5218cae4a7e3ae3c47dcd749e2efb",
  "update_time": "2025-05-10T11:50:00.341Z"
}